oslo_context/__init__.py
oslo_context/context.py
oslo_context/fixture.py
oslo_context/version.py
oslo_context/tests/__init__.py
oslo_context/tests/test_context.py
oslo_context/tests/test_fixture.py
oslo_context-6.0.0.dist-info/AUTHORS
oslo_context-6.0.0.dist-info/LICENSE
oslo_context-6.0.0.dist-info/METADATA
oslo_context-6.0.0.dist-info/WHEEL
oslo_context-6.0.0.dist-info/pbr.json
oslo_context-6.0.0.dist-info/top_level.txt
oslo_context-6.0.0.dist-info/RECORD
